koine_sdk/__init__.py
koine_sdk/_types.py
koine_sdk/client.py
koine_sdk/errors.py
koine_sdk/http.py
koine_sdk/object.py
koine_sdk/py.typed
koine_sdk/text.py
koine_sdk/types.py
koine_sdk/stream/__init__.py
koine_sdk/stream/sse.py
koine_sdk/stream/stream_object.py
koine_sdk/stream/types.py
koine_sdk-2.3.0.dist-info/METADATA
koine_sdk-2.3.0.dist-info/WHEEL
koine_sdk-2.3.0.dist-info/RECORD
