Metadata-Version: 2.4
Name: koine-sdk
Version: 2.3.0
Summary: Python SDK for Koine gateway
Project-URL: Homepage, https://github.com/pattern-zones-co/koine
Project-URL: Repository, https://github.com/pattern-zones-co/koine.git
Project-URL: Issues, https://github.com/pattern-zones-co/koine/issues
Author: Pattern Zones Co
License-Expression: AGPL-3.0-only OR LicenseRef-Commercial
Keywords: ai,anthropic,claude,claude-code,gateway,sdk
Classifier: Development Status :: 4 - Beta
Classifier: Framework :: AsyncIO
Classifier: Intended Audience :: Developers
Classifier: License :: OSI Approved :: GNU Affero General Public License v3
Classifier: Programming Language :: Python :: 3.11
Classifier: Programming Language :: Python :: 3.12
Classifier: Programming Language :: Python :: 3.13
Classifier: Typing :: Typed
Requires-Python: >=3.11
Requires-Dist: httpx==0.28.1
Requires-Dist: pydantic==2.12.5
Provides-Extra: dev
Requires-Dist: pyright==1.1.407; extra == 'dev'
Requires-Dist: pytest-asyncio==1.3.0; extra == 'dev'
Requires-Dist: pytest-cov==7.0.0; extra == 'dev'
Requires-Dist: pytest-httpx==0.36.0; extra == 'dev'
Requires-Dist: pytest==9.0.2; extra == 'dev'
Requires-Dist: python-dotenv==1.2.1; extra == 'dev'
Requires-Dist: ruff==0.14.10; extra == 'dev'
